pie_break/__init__.py
pie_break/pie_break.py
pie_break-1.0.1.data/scripts/piebreak
pie_break-1.0.1.dist-info/LICENSE
pie_break-1.0.1.dist-info/METADATA
pie_break-1.0.1.dist-info/WHEEL
pie_break-1.0.1.dist-info/top_level.txt
pie_break-1.0.1.dist-info/RECORD
