Metadata-Version: 2.1
Name: pie-break
Version: 1.0.1
Summary: An eye-catching break timer for the screen-bound
Home-page: https://github.com/sctrls/pie_break
Author: sctrls
Author-email: donot@email.me
License: MIT License
Classifier: Programming Language :: Python :: 3.8
Classifier: License :: OSI Approved :: MIT License
Classifier: Operating System :: OS Independent
License-File: LICENSE
